setup.py
omxsync/__init__.py
omxsync/broadcaster.py
omxsync/receiver.py
omxsync.egg-info/PKG-INFO
omxsync.egg-info/SOURCES.txt
omxsync.egg-info/dependency_links.txt
omxsync.egg-info/requires.txt
omxsync.egg-info/top_level.txt
omxsync.egg-info/zip-safe
test/test_broadcaster.py
test/test_receiver.py
test/test_sync.py