Metadata-Version: 1.0
Name: omxsync
Version: 0.1.1
Summary: Master/slave syncing of omxplayer instances over network
Home-page: http://github.com/markkorput/pyOmxSync
Author: Mark van de Korput
Author-email: dr.theman@gmail.com
License: MIT
Platform: UNKNOWN
